pydal_libsql/__about__.py
pydal_libsql/__init__.py
pydal_libsql/adapter_libsql.py
pydal_libsql-0.2.0.dist-info/METADATA
pydal_libsql-0.2.0.dist-info/WHEEL
pydal_libsql-0.2.0.dist-info/RECORD
