Metadata-Version: 2.3
Name: pydal-libsql
Version: 0.2.0
Summary: Custom pyDAL adapter for libsql (distributed SQLite)
Project-URL: Homepage, https://github.com/educationwarehouse/pydal-adapter-libsql
Author-email: Robin van der Noord <robin.vdn@educationwarehouse.nl>
Requires-Python: >=3.10
Requires-Dist: dbapi2abc
Requires-Dist: libsql-client
Requires-Dist: pydal
Provides-Extra: dev
Requires-Dist: hatch; extra == 'dev'
Requires-Dist: python-semantic-release<8; extra == 'dev'
Requires-Dist: su6[all]; extra == 'dev'
Requires-Dist: testcontainers; extra == 'dev'
